{
  "id": {
    "S": "767397734112-us-east-1-EC2Instance-i-0e46406d5f846f858"
  },
  "accountId": {
    "S": "767397734112"
  },
  "accountName": {
    "S": "Arquiteturas e Sistemas"
  },
  "amiName": {
    "S": "Migrated_Windows_Instance_"
  },
  "createdAt": {
    "S": "2025-09-01T11:27:46.000Z"
  },
  "cwAgentDiskDetected": {
    "BOOL": true
  },
  "cwAgentMemoryDetected": {
    "BOOL": true
  },
  "ebsStatus": {
    "S": "ok"
  },
  "healthChecksPassed": {
    "N": "3"
  },
  "healthChecksTotal": {
    "N": "3"
  },
  "healthStatus": {
    "S": "Healthy"
  },
  "iamRole": {
    "S": "SWOSystemsManagerRole"
  },
  "instanceId": {
    "S": "i-0e46406d5f846f858"
  },
  "instanceName": {
    "S": "aws-srv-dev-01 (Thiago)"
  },
  "instancePrivateIps": {
    "S": "[\"172.24.73.13\"]"
  },
  "instancePublicIps": {
    "S": "[]"
  },
  "instanceState": {
    "S": "running"
  },
  "instanceStatus": {
    "S": "ok"
  },
  "instanceType": {
    "S": "t3a.large"
  },
  "isWindows": {
    "BOOL": true
  },
  "lastUpdated": {
    "S": "2025-09-09T12:00:48.890Z"
  },
  "patchGroup": {
    "S": "1"
  },
  "platformDetails": {
    "S": "Windows"
  },
  "region": {
    "S": "us-east-1"
  },
  "resourceType": {
    "S": "EC2Instance"
  },
  "resourceTypeRegionId": {
    "S": "EC2Instance#us-east-1#i-0e46406d5f846f858"
  },
  "ssmLastPingTime": {
    "S": "2025-09-09T11:59:45.107Z"
  },
  "ssmPingStatus": {
    "S": "Online"
  },
  "ssmStatus": {
    "S": "Online"
  },
  "ssmVersion": {
    "S": "3.3.3050.0"
  },
  "swoBackup": {
    "S": "2"
  },
  "swoMonitor": {
    "S": "1"
  },
  "swoPatch": {
    "S": "1"
  },
  "swoRiskClass": {
    "S": "1"
  },
  "systemStatus": {
    "S": "ok"
  },
  "tags": {
    "S": "[{\"Key\": \"Billing-ASIS\", \"Value\": \"0\"}, {\"Key\": \"swoBackup\", \"Value\": \"2\"}, {\"Key\": \"Name\", \"Value\": \"aws-srv-dev-01 (Thiago)\"}, {\"Key\": \"aws:ec2launchtemplate:id\", \"Value\": \"lt-0e05ba3b885fa98ad\"}, {\"Key\": \"mgn.amazonaws.com-source-server\", \"Value\": \"s-30957504f3a3cb611\"}, {\"Key\": \"swoPatch\", \"Value\": \"1\"}, {\"Key\": \"PatchGroup\", \"Value\": \"1\"}, {\"Key\": \"AWSApplicationMigrationServiceManaged\", \"Value\": \"mgn.amazonaws.com\"}, {\"Key\": \"swoMonitor\", \"Value\": \"1\"}, {\"Key\": \"mgn.amazonaws.com-job\", \"Value\": \"mgnjob-3262ec90f6a9923e8\"}, {\"Key\": \"swoResize\", \"Value\": \"0\"}, {\"Key\": \"swoRiskClass\", \"Value\": \"1\"}, {\"Key\": \"map-migrated\", \"Value\": \"migDATH74P7VG\"}, {\"Key\": \"AWSApplicationMigrationServiceSourceServerID\", \"Value\": \"s-30957504f3a3cb611\"}, {\"Key\": \"aws:ec2launchtemplate:version\", \"Value\": \"4\"}]"
  },
  "updatedAt": {
    "S": "2025-09-09T12:00:48.890Z"
  }
}